odoo/addons/l10n_be_partner_identification/README.rst
odoo/addons/l10n_be_partner_identification/__init__.py
odoo/addons/l10n_be_partner_identification/__manifest__.py
odoo/addons/l10n_be_partner_identification/data/l10n_be_partner_identification.xml
odoo/addons/l10n_be_partner_identification/i18n/l10n_be_partner_identification.pot
odoo/addons/l10n_be_partner_identification/models/__init__.py
odoo/addons/l10n_be_partner_identification/models/res_partner_id_category.py
odoo/addons/l10n_be_partner_identification/static/description/icon.png
odoo/addons/l10n_be_partner_identification/tests/__init__.py
odoo/addons/l10n_be_partner_identification/tests/test_l10n_be_partner_identification.py
odoo13_addon_l10n_be_partner_identification-13.0.2.0.0.dist-info/METADATA
odoo13_addon_l10n_be_partner_identification-13.0.2.0.0.dist-info/WHEEL
odoo13_addon_l10n_be_partner_identification-13.0.2.0.0.dist-info/top_level.txt
odoo13_addon_l10n_be_partner_identification-13.0.2.0.0.dist-info/RECORD
