Metadata-Version: 2.1
Name: odoo13-addon-l10n-be-partner-identification
Version: 13.0.2.0.0
Summary: Belgium Partner Identification Numbers
Home-page: https://github.com/OCA/l10n-belgium
Author: ACSONE SA/NV,Odoo Community Association (OCA)
Author-email: support@odoo-community.org
License: AGPL-3
Platform: UNKNOWN
Classifier: Programming Language :: Python
Classifier: Framework :: Odoo
Classifier: License :: OSI Approved :: GNU Affero General Public License v3
Requires-Python: >=3.5
Requires-Dist: odoo13-addon-partner-identification
Requires-Dist: odoo (<13.1dev,>=13.0a)
